<DOMSymbolItem xmlns:xsi="http://www.w3.org/2001/XMLSchema-instance" xmlns="http://ns.adobe.com/xfl/2008/" name="Assets/Buttons/CRadiobutton Assets/TC_TObject__radioUp&amp;#032" itemID="5bbe7256-00000374" sourceFlashFilepath="../../../Projects FlashBuilder/TED2.1.0/Module_DedReason/DedReason_FLA/DedReason_FLA.xfl" sourceLibraryItemHRef="Buttons/CRadiobutton Assets/radioUp " sourceLastModified="1340990723" lastModified="1539207766" sourceItemID="00000000-ffffffff">
  <timeline>
    <DOMTimeline name="TC_TObject__radioUp&amp;#032">
      <layers>
        <DOMLayer name="Layer 1" color="#4FFF4F" current="true" isSelected="true">
          <frames>
            <DOMFrame index="0" keyMode="9728">
              <elements>
                <DOMShape isDrawingObject="true">
                  <fills>
                    <FillStyle index="1">
                      <SolidColor color="#FFFFFF"/>
                    </FillStyle>
                  </fills>
                  <strokes>
                    <StrokeStyle index="1">
                      <SolidStroke scaleMode="normal" weight="4" pixelHinting="true">
                        <fill>
                          <SolidColor color="#CCCCCC"/>
                        </fill>
                      </SolidStroke>
                    </StrokeStyle>
                  </strokes>
                  <edges>
                    <Edge fillStyle0="1" strokeStyle="1" edges="!2040 0|200 0!200 0[0 0 0 200!0 200|0 2060!0 2060[0 2260 200 2260!200 2260|2040 2260!2040 2260[2240 2260 2240 2060!2240 2060|2240 200!2240 200[2240 0 2040 0"/>
                  </edges>
                </DOMShape>
              </elements>
            </DOMFrame>
          </frames>
        </DOMLayer>
      </layers>
    </DOMTimeline>
  </timeline>
</DOMSymbolItem>